HIDRelay/__init__.py
HIDRelay/hid_relay.py
HIDRelay-1.0.0.0.dist-info/METADATA
HIDRelay-1.0.0.0.dist-info/WHEEL
HIDRelay-1.0.0.0.dist-info/top_level.txt
HIDRelay-1.0.0.0.dist-info/RECORD
