Metadata-Version: 2.1
Name: HIDRelay
Version: 1.0.0.0
Summary: Test Package
Home-page: UNKNOWN
Author: test
Author-email: 
License: MIT
Platform: UNKNOWN
Requires-Python: >=3
Requires-Dist: pywinusb
